localsql/__init__.py
localsql/localsql.py
localsql-0.2.5.data/scripts/localsql
localsql-0.2.5.dist-info/LICENSE
localsql-0.2.5.dist-info/METADATA
localsql-0.2.5.dist-info/WHEEL
localsql-0.2.5.dist-info/top_level.txt
localsql-0.2.5.dist-info/RECORD
