Metadata-Version: 2.1
Name: localsql
Version: 0.2.5
Summary: Querying local files using SQL
Home-page: https://github.com/localsql/localsql
Author: localsql
Author-email: author@example.com
License: BSD
Project-URL: Documentation, https://github.com/localsql/localsql/blob/master/README.md
Project-URL: Code, https://github.com/localsql/localsql
Project-URL: Issue tracker, https://github.com/localsql/localsql/issues
Platform: any
Classifier: License :: OSI Approved :: BSD License
Requires-Python: >=3.6
Requires-Dist: pandas
Requires-Dist: pandasql
Requires-Dist: openpyxl
Requires-Dist: prompt-toolkit
Requires-Dist: pygments
Requires-Dist: tableprint
Requires-Dist: argcomplete
